QtModularUiPack/__init__.py
QtModularUiPack/Framework/__init__.py
QtModularUiPack/Framework/Experiments/__init__.py
QtModularUiPack/Framework/Experiments/experiment_base.py
QtModularUiPack/Framework/Extensions/__init__.py
QtModularUiPack/Framework/Extensions/code_environment.py
QtModularUiPack/Framework/Extensions/killable_thread.py
QtModularUiPack/Framework/Extensions/observable_list.py
QtModularUiPack/Framework/Extensions/signal.py
QtModularUiPack/Framework/Extensions/singleton.py
QtModularUiPack/Framework/ImportTools/__init__.py
QtModularUiPack/Framework/ImportTools/module_manager.py
QtModularUiPack/Framework/ImportTools/utils.py
QtModularUiPack/Framework/Math/Spectrogram.py
QtModularUiPack/Framework/Math/__init__.py
QtModularUiPack/ModularApplications/__init__.py
QtModularUiPack/ModularApplications/ToolFrameViewModels/__init__.py
QtModularUiPack/ModularApplications/ToolFrameViewModels/experiment_frame_view_model.py
QtModularUiPack/ModularApplications/ToolFrameViewModels/hello_world_view_model.py
QtModularUiPack/ModularApplications/ToolFrameViewModels/tool_command_view_model.py
QtModularUiPack/ModularApplications/ToolsFrames/__init__.py
QtModularUiPack/ModularApplications/ToolsFrames/experiment_frame.py
QtModularUiPack/ModularApplications/ToolsFrames/hello_world_frame.py
QtModularUiPack/ModularApplications/ToolsFrames/tool_command_frame.py
QtModularUiPack/ViewModels/__init__.py
QtModularUiPack/ViewModels/base_context_aware_view_model.py
QtModularUiPack/ViewModels/base_view_model.py
QtModularUiPack/ViewModels/modular_application_view_model.py
QtModularUiPack/Widgets/__init__.py
QtModularUiPack/Widgets/code_editor.py
QtModularUiPack/Widgets/empty_frame.py
QtModularUiPack/Widgets/modular_application.py
QtModularUiPack/Widgets/modular_frame.py
QtModularUiPack/Widgets/modular_frame_host.py
QtModularUiPack/Widgets/plot_widget.py
QtModularUiPack/Widgets/py_graph_widget.py
QtModularUiPack/Widgets/utils.py
QtModularUiPack/Widgets/video_editor.py
QtModularUiPack-0.0.7.dist-info/LICENSE
QtModularUiPack-0.0.7.dist-info/METADATA
QtModularUiPack-0.0.7.dist-info/WHEEL
QtModularUiPack-0.0.7.dist-info/top_level.txt
QtModularUiPack-0.0.7.dist-info/RECORD
